Metadata-Version: 2.1
Name: birdvoxclassify
Version: 0.3.1
Summary: Species identification from bird flight call recordings
Home-page: https://github.com/BirdVox/birdvoxclassify
Author: Aurora Cramer, Vincent Lostanlen, Justin Salamon, Andrew Farnsworth, and Juan Pablo Bello
Author-email: jtcramer@nyu.edu
License: MIT
Project-URL: Source, https://github.com/BirdVox/birdvoxclassify
Project-URL: Tracker, https://github.com/BirdVox/birdvoxclassify/issues
Keywords: bioacoustics,audio signal processing,machine learning
Platform: UNKNOWN
Classifier: Development Status :: 3 - Alpha
Classifier: License :: OSI Approved :: MIT License
Classifier: Topic :: Multimedia :: Sound/Audio :: Analysis
Classifier: Programming Language :: Python :: 3
Classifier: Programming Language :: Python :: 3.6
Classifier: Programming Language :: Python :: 3.7
Classifier: Programming Language :: Python :: 3.8
Provides-Extra: docs
Provides-Extra: tests
